tensorfloe/__init__.py
tensorfloe/chatbot.py
tensorfloe/chatbot.txt
tensorfloe/gender.py
tensorfloe/gender.txt
tensorfloe/latent.py
tensorfloe/latent.txt
tensorfloe/pos.py
tensorfloe/pos.txt
tensorfloe/sentiment.py
tensorfloe/sentiment.txt
tensorfloe/skipgram.py
tensorfloe/skipgram.txt
tensorfloe/spam.py
tensorfloe/spam.txt
tensorfloe/summary.py
tensorfloe/summary.txt
tensorfloe/transformer.py
tensorfloe/transformer.txt
tensorfloe/word2vec.py
tensorfloe/word2vec.txt
tensorfloe-1.4.dist-info/METADATA
tensorfloe-1.4.dist-info/WHEEL
tensorfloe-1.4.dist-info/entry_points.txt
tensorfloe-1.4.dist-info/top_level.txt
tensorfloe-1.4.dist-info/RECORD
