Metadata-Version: 2.1
Name: tensorfloe
Version: 1.4
Summary: Description of your package
Home-page: https://github.com/Rehaaaan/tensorfloe/tree/master
Author: Your Name
Author-email: your@email.com
License: UNKNOWN
Platform: UNKNOWN
Classifier: Programming Language :: Python :: 3
Classifier: License :: OSI Approved :: MIT License
Classifier: Operating System :: OS Independent
